[
    {
        "pid" : "1",
        "title" : "how is the class?",
        "content" : "good",
        "user" : "yolo6969",
        "time" : 1582832190762,
        "type" : "text",
        "tags" : ["cs307", "cs240"],
        "count" : "10",
        "comments" : []
    },
    {
        "pid" : "2",
        "title" : "how is the class?",
        "content" : "good",
        "user" : "grr",
        "time" : 1582832190762,
        "type" : "text",
        "tags" : ["cs252"],
        "count" : "10",
        "comments" : []
    },
    {
        "pid" : "3",
        "title" : "how is the class?",
        "content" : "good",
        "user" : "tmaster",
        "time" : 1582832190762,
        "type" : "text",
        "tags" : ["cs240"],
        "count" : "10",
        "comments" : []
    },
    {
        "pid" : "4",
        "title" : "how is the class?",
        "content" : "good",
        "user" : "hulkbuster",
        "time" : 1582832190762,
        "type" : "text",
        "tags" : ["cs180"],
        "count" : "10",
        "comments" : []
    }
]